{
  "date": "2025-03-29",
  "projects": {
    "autodidak": {
      "totalLinesAdded": 60,
      "totalLinesRemoved": 0,
      "totalActiveTime": 8,
      "files": {
        "c:\\autodidak\\SiDesa\\database\\migrations\\0001_01_01_000000_create_users_table.php": [
          {
            "timestamp": "2025-03-29T14:40:35.649Z",
            "fileName": "c:\\autodidak\\SiDesa\\database\\migrations\\0001_01_01_000000_create_users_table.php",
            "fileType": ".php",
            "linesAdded": 50,
            "linesRemoved": 0,
            "projectName": "autodidak",
            "content": {
              "added": [],
              "removed": []
            },
            "duration": 0,
            "language": "php"
          },
          {
            "timestamp": "2025-03-29T14:42:23.455Z",
            "fileName": "c:\\autodidak\\SiDesa\\database\\migrations\\0001_01_01_000000_create_users_table.php",
            "fileType": ".php",
            "linesAdded": 1,
            "linesRemoved": 0,
            "projectName": "autodidak",
            "content": {
              "added": [],
              "removed": []
            },
            "duration": 2,
            "language": "php"
          },
          {
            "timestamp": "2025-03-29T14:45:36.369Z",
            "fileName": "c:\\autodidak\\SiDesa\\database\\migrations\\0001_01_01_000000_create_users_table.php",
            "fileType": ".php",
            "linesAdded": 1,
            "linesRemoved": 0,
            "projectName": "autodidak",
            "content": {
              "added": [],
              "removed": []
            },
            "duration": 4,
            "language": "php"
          },
          {
            "timestamp": "2025-03-29T14:47:29.351Z",
            "fileName": "c:\\autodidak\\SiDesa\\database\\migrations\\0001_01_01_000000_create_users_table.php",
            "fileType": ".php",
            "linesAdded": 8,
            "linesRemoved": 0,
            "projectName": "autodidak",
            "content": {
              "added": [],
              "removed": []
            },
            "duration": 2,
            "language": "php"
          }
        ]
      },
      "languageStats": {
        "php": 0
      },
      "changeFrequency": {
        "21": 0
      },
      "topFiles": [
        "c:\\autodidak\\SiDesa\\database\\migrations\\0001_01_01_000000_create_users_table.php"
      ],
      "averageChangeSize": 50
    }
  },
  "totalActiveTime": 0,
  "totalProjects": 1,
  "totalFiles": 1,
  "mostActiveHours": [
    21
  ],
  "mostUsedLanguages": [
    "php"
  ]
}